whisper_cpp_cli-0.0.3.data/scripts/whisper-cpp
whisper_cpp_cli-0.0.3.dist-info/METADATA
whisper_cpp_cli-0.0.3.dist-info/RECORD
whisper_cpp_cli-0.0.3.dist-info/WHEEL
whisper_cpp_cli-0.0.3.dist-info/licenses/LICENSE
whisper_cpp_cli.scripts/whisper-cpp
whisper_cpp/__init__.py
whisper_cpp/__main__.py
whisper_cpp_cli.libs/libgcc_s-8b50eaaa.so.1
whisper_cpp_cli.libs/libstdc++-8baf04f9.so.6.0.28
