Metadata-Version: 2.1
Name: whisper.cpp-cli
Version: 0.0.3
Summary: A Python package for the whisper.cpp CLI.
Author-Email: Charlie Marsh <charlie.r.marsh@gmail.com>
License: MIT License
Requires-Python: >=3.7
